{
  "index": {
    "js": [
      "/assets/js/1.050b9ff7.chunk.js",
      "/assets/js/0.a0e7f7f0.chunk.js",
      "/assets/js/index.bb3e04e4.js"
    ],
    "css": [
      "/assets/css/0.a0e7f7f0.css",
      "/assets/css/index.bb3e04e4.css"
    ]
  },
  "product": {
    "js": [
      "/assets/js/1.050b9ff7.chunk.js",
      "/assets/js/0.a0e7f7f0.chunk.js",
      "/assets/js/product.4a563484.js"
    ],
    "css": [
      "/assets/css/0.a0e7f7f0.css",
      "/assets/css/product.4a563484.css"
    ]
  }
}